line_profiler_pycharm/__init__.py
line_profiler_pycharm/_profile.py
line_profiler_pycharm-1.2.0.dist-info/LICENSE
line_profiler_pycharm-1.2.0.dist-info/METADATA
line_profiler_pycharm-1.2.0.dist-info/WHEEL
line_profiler_pycharm-1.2.0.dist-info/top_level.txt
line_profiler_pycharm-1.2.0.dist-info/RECORD
