Metadata-Version: 2.1
Name: line-profiler-pycharm
Version: 1.2.0
Summary: PyCharm Line Profiler helper package with which one can visualize profiles from the 'line-profiler' into PyCharm
Home-page: https://gitlab.com/line-profiler-pycharm/line-profiler-pycharm-python/
Author: Justen Ingels
Author-email: jhwj.ingels@gmail.com
Classifier: Programming Language :: Python :: 3
Classifier: License :: OSI Approved :: MIT License
Classifier: Operating System :: OS Independent
Requires-Python: >=3
License-File: LICENSE
Requires-Dist: line-profiler
